refiners/__init__.py
refiners/py.typed
refiners/fluxion/__init__.py
refiners/fluxion/context.py
refiners/fluxion/model_converter.py
refiners/fluxion/utils.py
refiners/fluxion/adapters/__init__.py
refiners/fluxion/adapters/adapter.py
refiners/fluxion/adapters/lora.py
refiners/fluxion/layers/__init__.py
refiners/fluxion/layers/activations.py
refiners/fluxion/layers/attentions.py
refiners/fluxion/layers/basics.py
refiners/fluxion/layers/chain.py
refiners/fluxion/layers/conv.py
refiners/fluxion/layers/converter.py
refiners/fluxion/layers/embedding.py
refiners/fluxion/layers/linear.py
refiners/fluxion/layers/maxpool.py
refiners/fluxion/layers/module.py
refiners/fluxion/layers/norm.py
refiners/fluxion/layers/padding.py
refiners/fluxion/layers/pixelshuffle.py
refiners/fluxion/layers/sampling.py
refiners/foundationals/__init__.py
refiners/foundationals/clip/__init__.py
refiners/foundationals/clip/bpe_simple_vocab_16e6.txt.gz
refiners/foundationals/clip/common.py
refiners/foundationals/clip/concepts.py
refiners/foundationals/clip/image_encoder.py
refiners/foundationals/clip/text_encoder.py
refiners/foundationals/clip/tokenizer.py
refiners/foundationals/dinov2/__init__.py
refiners/foundationals/dinov2/dinov2.py
refiners/foundationals/dinov2/vit.py
refiners/foundationals/latent_diffusion/__init__.py
refiners/foundationals/latent_diffusion/auto_encoder.py
refiners/foundationals/latent_diffusion/cross_attention.py
refiners/foundationals/latent_diffusion/freeu.py
refiners/foundationals/latent_diffusion/image_prompt.py
refiners/foundationals/latent_diffusion/lora.py
refiners/foundationals/latent_diffusion/model.py
refiners/foundationals/latent_diffusion/multi_diffusion.py
refiners/foundationals/latent_diffusion/range_adapter.py
refiners/foundationals/latent_diffusion/reference_only_control.py
refiners/foundationals/latent_diffusion/restart.py
refiners/foundationals/latent_diffusion/self_attention_guidance.py
refiners/foundationals/latent_diffusion/style_aligned.py
refiners-0.4.0.dist-info/METADATA
refiners-0.4.0.dist-info/WHEEL
refiners-0.4.0.dist-info/licenses/LICENSE
refiners-0.4.0.dist-info/RECORD
