Metadata-Version: 2.1
Name: refiners
Version: 0.4.0
Summary: The simplest way to train and run adapters on top of foundation models
Author-email: The Finegrain Team <bonjour@lagon.tech>
License-Expression: MIT
License-File: LICENSE
Classifier: Intended Audience :: Developers
Classifier: Intended Audience :: Science/Research
Classifier: License :: OSI Approved :: MIT License
Classifier: Programming Language :: Python :: 3.10
Classifier: Programming Language :: Python :: 3.11
Classifier: Topic :: Scientific/Engineering :: Artificial Intelligence
Classifier: Topic :: Software Development :: Libraries :: Python Modules
Classifier: Typing :: Typed
Requires-Python: >=3.10
Requires-Dist: jaxtyping>=0.2.23
Requires-Dist: packaging>=23.2
Requires-Dist: pillow>=10.1.0
Requires-Dist: safetensors>=0.4.0
Requires-Dist: torch>=2.1.1
Provides-Extra: conversion
Requires-Dist: diffusers>=0.26.1; extra == 'conversion'
Requires-Dist: requests>=2.26.0; extra == 'conversion'
Requires-Dist: segment-anything-py>=1.0; extra == 'conversion'
Requires-Dist: tqdm>=4.62.3; extra == 'conversion'
Requires-Dist: transformers>=4.35.2; extra == 'conversion'
Provides-Extra: doc
Requires-Dist: black>=24.1.1; extra == 'doc'
Requires-Dist: mkdocs-literate-nav>=0.6.1; extra == 'doc'
Requires-Dist: mkdocs-material>=9.5.6; extra == 'doc'
Requires-Dist: mkdocstrings[python]>=0.24.0; extra == 'doc'
Provides-Extra: test
Requires-Dist: diffusers>=0.26.1; extra == 'test'
Requires-Dist: invisible-watermark>=0.2.0; extra == 'test'
Requires-Dist: piq>=0.8.0; extra == 'test'
Requires-Dist: segment-anything-py>=1.0; extra == 'test'
Requires-Dist: torchvision>=0.16.1; extra == 'test'
Requires-Dist: transformers>=4.35.2; extra == 'test'
Provides-Extra: training
Requires-Dist: bitsandbytes>=0.41.2.post2; extra == 'training'
Requires-Dist: datasets>=2.15.0; extra == 'training'
Requires-Dist: loguru>=0.7.2; extra == 'training'
Requires-Dist: prodigyopt>=1.0; extra == 'training'
Requires-Dist: pydantic>=2.5.2; extra == 'training'
Requires-Dist: tomli>=2.0.1; extra == 'training'
Requires-Dist: torchvision>=0.16.1; extra == 'training'
Requires-Dist: wandb>=0.16.0; extra == 'training'
